CHANGES.txt
README.txt
TODO.txt
bootstrap.py
buildout.cfg
setup.py
test-plone-2.5.cfg
test-plone-3.3.x.cfg
test-plone-4.0.x.cfg
Products/__init__.py
Products.salesforcepfgadapter.egg-info/PKG-INFO
Products.salesforcepfgadapter.egg-info/SOURCES.txt
Products.salesforcepfgadapter.egg-info/dependency_links.txt
Products.salesforcepfgadapter.egg-info/entry_points.txt
Products.salesforcepfgadapter.egg-info/namespace_packages.txt
Products.salesforcepfgadapter.egg-info/not-zip-safe
Products.salesforcepfgadapter.egg-info/requires.txt
Products.salesforcepfgadapter.egg-info/top_level.txt
Products/salesforcepfgadapter/LICENSE.GPL
Products/salesforcepfgadapter/LICENSE.txt
Products/salesforcepfgadapter/__init__.py
Products/salesforcepfgadapter/config.py
Products/salesforcepfgadapter/configure.zcml
Products/salesforcepfgadapter/events.py
Products/salesforcepfgadapter/interfaces.py
Products/salesforcepfgadapter/messagefactory_.py
Products/salesforcepfgadapter/prepopulator.py
Products/salesforcepfgadapter/validators.py
Products/salesforcepfgadapter/Extensions/Install.py
Products/salesforcepfgadapter/Extensions/__init__.py
Products/salesforcepfgadapter/browser/__init__.py
Products/salesforcepfgadapter/browser/configure.zcml
Products/salesforcepfgadapter/browser/summary.pt
Products/salesforcepfgadapter/browser/summary.py
Products/salesforcepfgadapter/content/__init__.py
Products/salesforcepfgadapter/content/salesforcepfgadapter.py
Products/salesforcepfgadapter/i18n/plone-salesforcepfgadapter-de.po
Products/salesforcepfgadapter/i18n/plone-salesforcepfgadapter.pot
Products/salesforcepfgadapter/locales/salesforcepfgadapter.pot
Products/salesforcepfgadapter/locales/de/LC_MESSAGES/salesforcepfgadapter.mo
Products/salesforcepfgadapter/locales/de/LC_MESSAGES/salesforcepfgadapter.po
Products/salesforcepfgadapter/locales/en/LC_MESSAGES/salesforcepfgadapter.mo
Products/salesforcepfgadapter/locales/en/LC_MESSAGES/salesforcepfgadapter.po
Products/salesforcepfgadapter/migrations/__init__.py
Products/salesforcepfgadapter/migrations/migrateUpTo10rc1.py
Products/salesforcepfgadapter/migrations/migrateUpTo15a1.py
Products/salesforcepfgadapter/profiles/default/factorytool.xml
Products/salesforcepfgadapter/profiles/default/metadata.xml
Products/salesforcepfgadapter/profiles/default/propertiestool.xml
Products/salesforcepfgadapter/profiles/default/skins.xml
Products/salesforcepfgadapter/profiles/default/types.xml
