Metadata-Version: 1.0
Name: Products.salesforcepfgadapter
Version: 1.9.0
Summary: PloneFormGen adapter allowing for creation of arbitrary Salesforce.com         records based on data collected from a web form
Home-page: http://groups.google.com/group/plonesf
Author: Plone/Salesforce Integration Group
Author-email: plonesf@googlegroups.com
License: GPL
Keywords: Zope CMF Plone Salesforce.com CRM PloneFormGen forms integration
Platform: UNKNOWN
Classifier: Programming Language :: Python
Classifier: Topic :: Software Development :: Libraries :: Python Modules
Classifier: Framework :: Zope2
Classifier: Framework :: Plone
